odoo10_addon_base_report_to_printer-10.0.2.0.2-py2.7-nspkg.pth
odoo/addons/base_report_to_printer/README.rst
odoo/addons/base_report_to_printer/__init__.py
odoo/addons/base_report_to_printer/__manifest__.py
odoo/addons/base_report_to_printer/data/printing_data.xml
odoo/addons/base_report_to_printer/demo/report.xml
odoo/addons/base_report_to_printer/i18n/am.po
odoo/addons/base_report_to_printer/i18n/base_report_to_printer.pot
odoo/addons/base_report_to_printer/i18n/bg.po
odoo/addons/base_report_to_printer/i18n/ca.po
odoo/addons/base_report_to_printer/i18n/de.po
odoo/addons/base_report_to_printer/i18n/el_GR.po
odoo/addons/base_report_to_printer/i18n/es.po
odoo/addons/base_report_to_printer/i18n/es_ES.po
odoo/addons/base_report_to_printer/i18n/fi.po
odoo/addons/base_report_to_printer/i18n/fr.po
odoo/addons/base_report_to_printer/i18n/gl.po
odoo/addons/base_report_to_printer/i18n/hr.po
odoo/addons/base_report_to_printer/i18n/hr_HR.po
odoo/addons/base_report_to_printer/i18n/it.po
odoo/addons/base_report_to_printer/i18n/nl.po
odoo/addons/base_report_to_printer/i18n/nl_NL.po
odoo/addons/base_report_to_printer/i18n/pt.po
odoo/addons/base_report_to_printer/i18n/pt_BR.po
odoo/addons/base_report_to_printer/i18n/pt_PT.po
odoo/addons/base_report_to_printer/i18n/sl.po
odoo/addons/base_report_to_printer/i18n/tr.po
odoo/addons/base_report_to_printer/i18n/zh_CN.po
odoo/addons/base_report_to_printer/models/__init__.py
odoo/addons/base_report_to_printer/models/ir_actions_report_xml.py
odoo/addons/base_report_to_printer/models/printing_action.py
odoo/addons/base_report_to_printer/models/printing_job.py
odoo/addons/base_report_to_printer/models/printing_printer.py
odoo/addons/base_report_to_printer/models/printing_report_xml_action.py
odoo/addons/base_report_to_printer/models/printing_server.py
odoo/addons/base_report_to_printer/models/report.py
odoo/addons/base_report_to_printer/models/res_users.py
odoo10_addon_base_report_to_printer-10.0.2.0.2.dist-info/DESCRIPTION.rst
odoo10_addon_base_report_to_printer-10.0.2.0.2.dist-info/METADATA
odoo10_addon_base_report_to_printer-10.0.2.0.2.dist-info/RECORD
odoo10_addon_base_report_to_printer-10.0.2.0.2.dist-info/WHEEL
odoo10_addon_base_report_to_printer-10.0.2.0.2.dist-info/metadata.json
odoo10_addon_base_report_to_printer-10.0.2.0.2.dist-info/namespace_packages.txt
odoo10_addon_base_report_to_printer-10.0.2.0.2.dist-info/top_level.txt
