Metadata-Version: 2.0
Name: odoo10-addon-base-report-to-printer
Version: 10.0.2.0.2
Summary: Report to printer
Home-page: https://github.com/OCA/report-print-send
Author: Agile Business Group & Domsense, Pegueroles SCP, NaN, LasLabs, Tecnativa, Odoo Community Association (OCA)
Author-email: support@odoo-community.org
License: AGPL-3
Platform: UNKNOWN
Classifier: Programming Language :: Python
Classifier: Framework :: Odoo
Classifier: License :: OSI Approved :: GNU Affero General Public License v3
Requires-Python: ~=2.7
Requires-Dist: odoo (<10.1dev,>=10.0)
Requires-Dist: pycups
